astro/__init__.py
astro/_version.py
astro/audio.py
astro/settings.py
astro/types.py
astro/video.py
astro/_mappings/__init__.py
astro/_mappings/base_model.py
astro/_mappings/chat_completion.py
astro/_mappings/types.py
astro/ai/__init__.py
astro/ai/audio.py
astro/ai/images.py
astro/ai/text.py
astro/ai/prompts/audio_prompts.py
astro/ai/prompts/image_prompts.py
astro/ai/prompts/text_prompts.py
astro/ai/prompts/vision_prompts.py
astro/beta/__init__.py
astro/beta/vision.py
astro/beta/ai_flow/__init__.py
astro/beta/ai_flow/ai_flow.py
astro/beta/ai_flow/ai_task.py
astro/beta/applications/__init__.py
astro/beta/applications/applications.py
astro/beta/applications/planner.py
astro/beta/applications/state/__init__.py
astro/beta/applications/state/disk.py
astro/beta/applications/state/json_block.py
astro/beta/applications/state/state.py
astro/beta/assistants/__init__.py
astro/beta/assistants/assistants.py
astro/beta/assistants/formatting.py
astro/beta/assistants/handlers.py
astro/beta/assistants/runs.py
astro/beta/assistants/threads.py
astro/cli/__init__.py
astro/cli/assistants.py
astro/cli/threads.py
astro/client/__init__.py
astro/client/openai.py
astro/tools/__init__.py
astro/tools/assistants.py
astro/tools/chroma.py
astro/tools/code.py
astro/tools/filesystem.py
astro/tools/github.py
astro/utilities/__init__.py
astro/utilities/asyncio.py
astro/utilities/context.py
astro/utilities/images.py
astro/utilities/jinja.py
astro/utilities/logging.py
astro/utilities/mapping.py
astro/utilities/openai.py
astro/utilities/pydantic.py
astro/utilities/python.py
astro/utilities/slack.py
astro/utilities/strings.py
astro/utilities/testing.py
astro/utilities/tools.py
askastro-1.0.0.dist-info/LICENSE
askastro-1.0.0.dist-info/METADATA
askastro-1.0.0.dist-info/WHEEL
askastro-1.0.0.dist-info/entry_points.txt
askastro-1.0.0.dist-info/top_level.txt
askastro-1.0.0.dist-info/RECORD
