Metadata-Version: 2.1
Name: askastro
Version: 1.0.0
Summary: A lightweight AI engineering toolkit for building natural language interfaces that are reliable, scalable, and easy to trust.
License: Apache License
Project-URL: Code, https://github.com/kozmoai/astro
Project-URL: Documentation, https://www.askastro.ai
Keywords: ai,chatbot,llm,NLP,natural language processing
Classifier: Programming Language :: Python :: 3 :: Only
Classifier: Topic :: Scientific/Engineering :: Artificial Intelligence
Requires-Python: >=3.9
License-File: LICENSE
Requires-Dist: cachetools >=5
Requires-Dist: fastapi
Requires-Dist: httpx >=0.24.1
Requires-Dist: jinja2 >=3.1.2
Requires-Dist: jsonpatch >=1.33
Requires-Dist: openai >=1.4.0
Requires-Dist: pydantic >=2.4.2
Requires-Dist: pydantic-settings
Requires-Dist: rich >=12
Requires-Dist: tiktoken >=0.4.0
Requires-Dist: typer >=0.9.0
Requires-Dist: typing-extensions >=4.0.0
Requires-Dist: tzdata >=2023.3
Requires-Dist: uvicorn >=0.22.0
Requires-Dist: partialjson >=0.0.5
Provides-Extra: audio
Requires-Dist: SpeechRecognition >=3.10 ; extra == 'audio'
Requires-Dist: PyAudio >=0.2.11 ; extra == 'audio'
Requires-Dist: playsound >=1.0 ; extra == 'audio'
Requires-Dist: wheel >=0.43.0 ; extra == 'audio'
Requires-Dist: PyObjC ; extra == 'audio'
Requires-Dist: pydub >=0.25 ; extra == 'audio'
Requires-Dist: simpleaudio >=1.0 ; extra == 'audio'
Provides-Extra: chromadb
Requires-Dist: chromadb ; extra == 'chromadb'
Provides-Extra: dev
Requires-Dist: askastro[tests] ; extra == 'dev'
Requires-Dist: black[jupyter] ; extra == 'dev'
Requires-Dist: ipython ; extra == 'dev'
Requires-Dist: mkdocs-autolinks-plugin ~=0.7 ; extra == 'dev'
Requires-Dist: mkdocs-awesome-pages-plugin ~=2.8 ; extra == 'dev'
Requires-Dist: mkdocs-markdownextradata-plugin ~=0.2 ; extra == 'dev'
Requires-Dist: mkdocs-jupyter >=0.24.1 ; extra == 'dev'
Requires-Dist: mkdocs-material[imaging] >=9.1.17 ; extra == 'dev'
Requires-Dist: mkdocstrings[python] ~=0.22 ; extra == 'dev'
Requires-Dist: pdbpp ~=0.10 ; extra == 'dev'
Requires-Dist: pre-commit <4.0,>=2.21 ; extra == 'dev'
Requires-Dist: pydantic[dotenv] ; extra == 'dev'
Requires-Dist: ruff ; extra == 'dev'
Provides-Extra: generator
Requires-Dist: datamodel-code-generator >=0.20.0 ; extra == 'generator'
Provides-Extra: nebulaconsole
Requires-Dist: nebulaconsole >=1.0.0 ; extra == 'nebulaconsole'
Provides-Extra: slackbot
Requires-Dist: astro[nebula] ; extra == 'slackbot'
Requires-Dist: numpy ; extra == 'slackbot'
Requires-Dist: astro[chromadb] ; extra == 'slackbot'
Provides-Extra: tests
Requires-Dist: pytest-asyncio !=0.22.0,<0.23.0,>=0.18.2 ; extra == 'tests'
Requires-Dist: pytest-env <2.0,>=0.8 ; extra == 'tests'
Requires-Dist: pytest-rerunfailures <14,>=10 ; extra == 'tests'
Requires-Dist: pytest-sugar <2.0,>=0.9 ; extra == 'tests'
Requires-Dist: pytest ~=7.3.1 ; extra == 'tests'
Requires-Dist: pytest-timeout ; extra == 'tests'
Requires-Dist: pytest-xdist ; extra == 'tests'
Provides-Extra: video
Requires-Dist: opencv-python >=4.5 ; extra == 'video'
